py_alpaca_api/__init__.py
py_alpaca_api/exceptions.py
py_alpaca_api/py.typed
py_alpaca_api/cache/__init__.py
py_alpaca_api/cache/cache_config.py
py_alpaca_api/cache/cache_manager.py
py_alpaca_api/http/feed_manager.py
py_alpaca_api/http/requests.py
py_alpaca_api/models/account_activity_model.py
py_alpaca_api/models/account_config_model.py
py_alpaca_api/models/account_model.py
py_alpaca_api/models/asset_model.py
py_alpaca_api/models/clock_model.py
py_alpaca_api/models/corporate_action_model.py
py_alpaca_api/models/model_utils.py
py_alpaca_api/models/order_model.py
py_alpaca_api/models/position_model.py
py_alpaca_api/models/quote_model.py
py_alpaca_api/models/snapshot_model.py
py_alpaca_api/models/trade_model.py
py_alpaca_api/models/watchlist_model.py
py_alpaca_api/stock/__init__.py
py_alpaca_api/stock/assets.py
py_alpaca_api/stock/auctions.py
py_alpaca_api/stock/history.py
py_alpaca_api/stock/latest_quote.py
py_alpaca_api/stock/logos.py
py_alpaca_api/stock/metadata.py
py_alpaca_api/stock/predictor.py
py_alpaca_api/stock/quotes.py
py_alpaca_api/stock/screener.py
py_alpaca_api/stock/snapshots.py
py_alpaca_api/stock/trades.py
py_alpaca_api/trading/__init__.py
py_alpaca_api/trading/account.py
py_alpaca_api/trading/corporate_actions.py
py_alpaca_api/trading/market.py
py_alpaca_api/trading/news.py
py_alpaca_api/trading/orders.py
py_alpaca_api/trading/positions.py
py_alpaca_api/trading/recommendations.py
py_alpaca_api/trading/watchlists.py
py_alpaca_api-3.0.1.dist-info/METADATA
py_alpaca_api-3.0.1.dist-info/WHEEL
py_alpaca_api-3.0.1.dist-info/licenses/LICENSE
py_alpaca_api-3.0.1.dist-info/RECORD
