Metadata-Version: 2.4
Name: py-alpaca-api
Version: 3.0.1
Summary: A modern Python wrapper for the Alpaca Trading API with 100% coverage of Trading and Market Data endpoints
Project-URL: Homepage, https://github.com/TexasCoding/py-alpaca-api
Project-URL: Documentation, https://py-alpaca-api.readthedocs.io
Project-URL: Repository, https://github.com/TexasCoding/py-alpaca-api
Project-URL: Issues, https://github.com/TexasCoding/py-alpaca-api/issues
Project-URL: Changelog, https://github.com/TexasCoding/py-alpaca-api/blob/main/CHANGELOG.md
Author-email: TexasCoding <jeff@texascoding.com>
Maintainer-email: TexasCoding <jeff@texascoding.com>
License: MIT
License-File: LICENSE
Keywords: algorithmic-trading,alpaca,api,backtesting,finance,market-data,paper-trading,quantitative-finance,stocks,trading
Classifier: Development Status :: 5 - Production/Stable
Classifier: Intended Audience :: Developers
Classifier: Intended Audience :: Financial and Insurance Industry
Classifier: License :: OSI Approved :: MIT License
Classifier: Operating System :: OS Independent
Classifier: Programming Language :: Python :: 3
Classifier: Programming Language :: Python :: 3.10
Classifier: Programming Language :: Python :: 3.11
Classifier: Programming Language :: Python :: 3.12
Classifier: Topic :: Office/Business :: Financial
Classifier: Topic :: Office/Business :: Financial :: Investment
Classifier: Topic :: Software Development :: Libraries :: Python Modules
Classifier: Typing :: Typed
Requires-Python: >=3.10
Requires-Dist: beautifulsoup4>=4.12.3
Requires-Dist: numpy>=2.1.1
Requires-Dist: pandas>=2.2.3
Requires-Dist: pendulum>=3.0.0
Requires-Dist: prophet>=1.1.5
Requires-Dist: redis>=6.4.0
Requires-Dist: requests-cache>=1.2.1
Requires-Dist: requests-ratelimiter>=0.7.0
Requires-Dist: requests>=2.32.3
Requires-Dist: yfinance>=0.2.43
Provides-Extra: dev
Requires-Dist: hypothesis>=6.112.1; extra == 'dev'
Requires-Dist: mypy>=1.11.0; extra == 'dev'
Requires-Dist: pre-commit>=3.8.0; extra == 'dev'
Requires-Dist: pytest-cov>=5.0.0; extra == 'dev'
Requires-Dist: pytest-mock>=3.14.0; extra == 'dev'
Requires-Dist: pytest>=8.3.3; extra == 'dev'
Requires-Dist: ruff>=0.6.8; extra == 'dev'
Requires-Dist: types-beautifulsoup4>=4.12.0; extra == 'dev'
Requires-Dist: types-requests>=2.32.0; extra == 'dev'
Provides-Extra: docs
Requires-Dist: myst-parser>=4.0.1; extra == 'docs'
Requires-Dist: nbsphinx>=0.9.7; extra == 'docs'
Requires-Dist: sphinx-autoapi>=3.6.0; extra == 'docs'
Requires-Dist: sphinx-rtd-theme>=3.0.2; extra == 'docs'
Requires-Dist: sphinx>=8.1.3; extra == 'docs'
